satosacontrib/__init__.py
satosacontrib/perun/__init__.py
satosacontrib/perun/addons/__init__.py
satosacontrib/perun/addons/extended_introspection_response.py
satosacontrib/perun/addons/userinfo_perun_updates.py
satosacontrib/perun/backends/__init__.py
satosacontrib/perun/backends/seznam.py
satosacontrib/perun/micro_services/__init__.py
satosacontrib/perun/micro_services/attribute_typing_microservice.py
satosacontrib/perun/micro_services/auth_event_logging_microservice.py
satosacontrib/perun/micro_services/auth_switcher_lite.py
satosacontrib/perun/micro_services/cardinality_single_microservice.py
satosacontrib/perun/micro_services/compute_eligibility.py
satosacontrib/perun/micro_services/context_attributes_microservice.py
satosacontrib/perun/micro_services/forward_authorization_params_microservice.py
satosacontrib/perun/micro_services/is_eligible_microservice.py
satosacontrib/perun/micro_services/multi_idphint_microservice.py
satosacontrib/perun/micro_services/nameid_attribute_microservice.py
satosacontrib/perun/micro_services/persist_authorization_params_microservice.py
satosacontrib/perun/micro_services/proxystatistics_microservice.py
satosacontrib/perun/micro_services/requester_client_id_microservice.py
satosacontrib/perun/micro_services/session_started_with_microservice.py
satosacontrib/perun/micro_services/idm/__init__.py
satosacontrib/perun/micro_services/idm/additional_identifiers.py
satosacontrib/perun/micro_services/idm/attributes.py
satosacontrib/perun/micro_services/idm/ensure_member.py
satosacontrib/perun/micro_services/idm/entitlement.py
satosacontrib/perun/micro_services/idm/is_banned_microservice.py
satosacontrib/perun/micro_services/idm/perun_user.py
satosacontrib/perun/micro_services/idm/sp_authorization.py
satosacontrib/perun/micro_services/idm/update_user_ext_source.py
satosacontrib/perun/utils/AuthEventLoggingDbModels.py
satosacontrib/perun/utils/ConfigStore.py
satosacontrib/perun/utils/CurlConnector.py
satosacontrib.perun-4.3.2.dist-info/LICENSE
satosacontrib.perun-4.3.2.dist-info/METADATA
satosacontrib.perun-4.3.2.dist-info/WHEEL
satosacontrib.perun-4.3.2.dist-info/top_level.txt
satosacontrib.perun-4.3.2.dist-info/RECORD
