Metadata-Version: 2.1
Name: satosacontrib.perun
Version: 4.3.2
Summary: Microservices, backends and add-ons for SATOSA authentication proxy
Home-page: https://gitlab.ics.muni.cz/perun/perun-proxyidp/satosacontrib-perun.git
Requires-Python: >=3.9
License-File: LICENSE
Requires-Dist: setuptools
Requires-Dist: SATOSA ~=8.1
Requires-Dist: pysaml2 ~=7.1
Requires-Dist: requests ~=2.28
Requires-Dist: perun.connector ~=3.8
Requires-Dist: PyYAML ~=6.0
Requires-Dist: SQLAlchemy ~=2.0
Requires-Dist: jwcrypto ~=1.3
Requires-Dist: natsort ~=8.4.0
Requires-Dist: python-dateutil ~=2.8
Requires-Dist: geoip2 ~=4.6
Requires-Dist: user-agents ~=2.2
Requires-Dist: pymongo <5,>=3.13.0
